couler/__init__.py
couler/_version.py
couler/argo.py
couler/argo_submitter.py
couler/docker_submitter.py
couler/core/__init__.py
couler/core/config.py
couler/core/constants.py
couler/core/proto_repr.py
couler/core/run_templates.py
couler/core/states.py
couler/core/step_update_utils.py
couler/core/utils.py
couler/core/workflow_validation_utils.py
couler/core/syntax/__init__.py
couler/core/syntax/concurrent.py
couler/core/syntax/conditional.py
couler/core/syntax/dag.py
couler/core/syntax/exit_handler.py
couler/core/syntax/loop.py
couler/core/syntax/predicates.py
couler/core/syntax/recursion.py
couler/core/syntax/volume.py
couler/core/templates/__init__.py
couler/core/templates/affinity.py
couler/core/templates/artifact.py
couler/core/templates/cache.py
couler/core/templates/container.py
couler/core/templates/job.py
couler/core/templates/output.py
couler/core/templates/script.py
couler/core/templates/secret.py
couler/core/templates/step.py
couler/core/templates/template.py
couler/core/templates/volume.py
couler/core/templates/volume_claim.py
couler/core/templates/workflow.py
couler/proto/__init__.py
couler/proto/couler_pb2.py
couler_scanflow-0.1.2.dist-info/AUTHORS
couler_scanflow-0.1.2.dist-info/LICENSE
couler_scanflow-0.1.2.dist-info/METADATA
couler_scanflow-0.1.2.dist-info/WHEEL
couler_scanflow-0.1.2.dist-info/top_level.txt
couler_scanflow-0.1.2.dist-info/RECORD
