Metadata-Version: 2.1
Name: couler-scanflow
Version: 0.1.2
Summary: Unified Interface for Constructing and Managing Workflows
Home-page: UNKNOWN
License: UNKNOWN
Platform: UNKNOWN
Requires-Python: >=3.6
Requires-Dist: pyaml
Requires-Dist: kubernetes (>=11.0.0)
Requires-Dist: docker (==4.1.0)
Requires-Dist: Deprecated
Provides-Extra: develop
Requires-Dist: pre-commit ; extra == 'develop'
Requires-Dist: pytest ; extra == 'develop'
Requires-Dist: pytest-cov ; extra == 'develop'
Requires-Dist: Deprecated ; extra == 'develop'
Requires-Dist: protobuf ; extra == 'develop'
Requires-Dist: argo-workflows (==3.5.1) ; extra == 'develop'
Requires-Dist: mkdocs (==1.1.2) ; extra == 'develop'
Requires-Dist: mkdocs-material (==7.1.3) ; extra == 'develop'
